apps
superdesk
