Metadata-Version: 1.1
Name: Superdesk-Server
Version: 0.1.6
Summary: Superdesk REST API server
Home-page: https://github.com/superdesk/superdesk-server
Author: petr jasek
Author-email: petr.jasek@sourcefabric.org
License: GPLv3
Platform: any
Classifier: Development Status :: 4 - Beta
Classifier: Environment :: Web Environment
Classifier: Intended Audience :: Developers
Classifier: License :: OSI Approved :: GNU General Public License v3 (GPLv3)
Classifier: Operating System :: OS Independent
Classifier: Programming Language :: Python
Classifier: Programming Language :: Python :: 3
Classifier: Topic :: Internet :: WWW/HTTP :: Dynamic Content
